hiviorm/__init__.py
hiviorm-0.0.0.dist-info/METADATA
hiviorm-0.0.0.dist-info/WHEEL
hiviorm-0.0.0.dist-info/top_level.txt
hiviorm-0.0.0.dist-info/RECORD
